CHANGES.txt
LICENSE.txt
MANIFEST.in
setup.cfg
setup.py
django_json_redirects/__init__.py
django_json_redirects/redirects.py
django_json_redirects.egg-info/PKG-INFO
django_json_redirects.egg-info/SOURCES.txt
django_json_redirects.egg-info/dependency_links.txt
django_json_redirects.egg-info/requires.txt
django_json_redirects.egg-info/top_level.txt