Metadata-Version: 1.0
Name: django-json-redirects
Version: 0.3
Summary: A simple redirects utility that uses a json file for redirects definitions
Home-page: https://github.com/ubuntudesign/django-json-redirects
Author: Tris
Author-email: tristram.oaten@canonical.com
License: UNKNOWN
Platform: UNKNOWN
